math_build02/__init__.py
math_build02/math_tool.py
math_build02/math_tool02.py
math_build02-0.1.0.dist-info/METADATA
math_build02-0.1.0.dist-info/WHEEL
math_build02-0.1.0.dist-info/entry_points.txt
math_build02-0.1.0.dist-info/RECORD
