Metadata-Version: 2.4
Name: math-build02
Version: 0.1.0
Summary: Add your description here
Requires-Python: >=3.11
